multiparse/__init__.py
multiparse/decoders.py
multiparse/exceptions.py
multiparse/multipart.py
multiparse/tests/__init__.py
multiparse/tests/compat.py
multiparse/tests/test_multipart.py
multiparse-2022.1.dist-info/LICENSE
multiparse-2022.1.dist-info/METADATA
multiparse-2022.1.dist-info/WHEEL
multiparse-2022.1.dist-info/top_level.txt
multiparse-2022.1.dist-info/RECORD
