Metadata-Version: 2.1
Name: multiparse
Version: 2022.1
Summary: Nifty streaming parser for Python
Home-page: https://multiparse.rtfd.io
Author: Gerrishon Sirere
Author-email: secretum.inc@pm.me
Maintainer: Secretum Inc.
Maintainer-email: secretum.inc@pm.me
License: MIT
Project-URL: Donate, https://tinyurl.com/ygaj5fwj
Project-URL: Documentation, https://multiparse.rtfd.io
Project-URL: Changes, https://multiparse.readthedocs.io/en/latest/changes.html
Project-URL: Source Code, https://github.com/secretum-inc/multiparse
Project-URL: Issue Tracker, https://github.com/secretum-inc/multiparse/issues/
Project-URL: Twitter, https://twitter.com/secretum_inc
Project-URL: Chat, https://gitter.im/secretum-inc
Platform: UNKNOWN
Classifier: Development Status :: 5 - Production/Stable
Classifier: Environment :: Web Environment
Classifier: Intended Audience :: Developers
Classifier: License :: OSI Approved :: MIT License
Classifier: Operating System :: OS Independent
Classifier: Programming Language :: Python
Requires-Python: >=3.6.1
License-File: LICENSE
Requires-Dist: quo
Requires-Dist: six
Requires-Dist: importlib-metadata ; python_version < "3.8"
